sav/__init__.py
sav/cli.py
sav/core/__init__.py
sav/core/commit.py
sav/core/config.py
sav/core/db.py
sav/core/fingerprint.py
sav/core/metrics.py
sav/core/policy.py
sav/core/repo.py
sav/utils/__init__.py
sav/utils/diff.py
savai-0.1.0.dist-info/licenses/LICENSE
savai-0.1.0.dist-info/METADATA
savai-0.1.0.dist-info/WHEEL
savai-0.1.0.dist-info/entry_points.txt
savai-0.1.0.dist-info/top_level.txt
savai-0.1.0.dist-info/RECORD
